detect_v1/__init__.py
detect_v1/api_client.py
detect_v1/configuration.py
detect_v1/rest.py
detect_v1/api/__init__.py
detect_v1/api/default_api.py
detect_v1/models/__init__.py
detect_v1/models/detection.py
detect_v1/models/detection_details.py
detect_v1/models/detections.py
detect_v1/models/error.py
detect_v1/models/host.py
detect_v1/models/host_artifact.py
detect_v1/models/hosts.py
detect_v1/models/system_info.py
detect_v2/__init__.py
detect_v2/api_client.py
detect_v2/configuration.py
detect_v2/rest.py
detect_v2/api/__init__.py
detect_v2/api/default_api.py
detect_v2/models/__init__.py
detect_v2/models/detection.py
detect_v2/models/detections.py
detect_v2/models/error.py
detect_v2/models/hosts.py
detect_v2/models/proxies.py
detect_v2/models/proxies_body.py
detect_v2/models/proxies_body_proxy.py
detect_v2/models/proxies_meta.py
detect_v2/models/proxy.py
detect_v2/models/threat_feed.py
detect_v2/models/threat_feeds.py
detect_v2/models/threat_feeds_body.py
vectra_api_client/__init__.py
vectra_api_client/apis.py
vectra_api_client-0.9.0.dist-info/LICENSE
vectra_api_client-0.9.0.dist-info/METADATA
vectra_api_client-0.9.0.dist-info/WHEEL
vectra_api_client-0.9.0.dist-info/top_level.txt
vectra_api_client-0.9.0.dist-info/RECORD
