Metadata-Version: 2.1
Name: vectra-api-client
Version: 0.9.0
Summary: Vectra API Client
Home-page: https://github.com/vicyap/vectra_api_client
Author: Victor Yap
Author-email: victor@vicyap.com
License: MIT license
Keywords: vectra_api_client
Platform: UNKNOWN
Classifier: Development Status :: 2 - Pre-Alpha
Classifier: Intended Audience :: Developers
Classifier: License :: OSI Approved :: MIT License
Classifier: Natural Language :: English
Classifier: Programming Language :: Python :: 2
Classifier: Programming Language :: Python :: 2.7
Classifier: Programming Language :: Python :: 3
Classifier: Programming Language :: Python :: 3.4
Classifier: Programming Language :: Python :: 3.5
Classifier: Programming Language :: Python :: 3.6
Classifier: Programming Language :: Python :: 3.7
Requires-Dist: certifi (>=14.05.14)
Requires-Dist: python-dateutil (>=2.5.3)
Requires-Dist: requests (==2.20.0)
Requires-Dist: setuptools (>=21.0.0)
Requires-Dist: six (>=1.10)
Requires-Dist: urllib3 (>=1.15.1)
